sneakydog_primitives_demo/__init__.py
sneakydog_primitives_demo/annotation_id.py
sneakydog_primitives_demo/classify_id.py
sneakydog_primitives_demo/datasets_id.py
sneakydog_primitives_demo/date_time.py
sneakydog_primitives_demo/email.py
sneakydog_primitives_demo/model_id.py
sneakydog_primitives_demo/orm.py
sneakydog_primitives_demo/password.py
sneakydog_primitives_demo/project_id.py
sneakydog_primitives_demo/resources_id.py
sneakydog_primitives_demo/task_id.py
sneakydog_primitives_demo/trainings_id.py
sneakydog_primitives_demo/user_id.py
sneakydog_primitives_demo/value_objects.py
sneakydog_primitives_demo-0.1.6.dist-info/METADATA
sneakydog_primitives_demo-0.1.6.dist-info/WHEEL
sneakydog_primitives_demo-0.1.6.dist-info/RECORD
