Metadata-Version: 2.4
Name: sneakydog-primitives-demo
Version: 0.1.6
Summary: Add your description here
Project-URL: Homepage, https://github.com/yourusername/your-package
Author-email: dfz <your.email@example.com>
Requires-Python: >=3.10
Requires-Dist: pydantic>=2.11.7
Requires-Dist: pytest>=8.4.1
Requires-Dist: sqlalchemy>=2.0.41
